algoaid/__init__.py
algoaid/analysis.py
algoaid/edge.py
algoaid/graph.py
algoaid/node.py
algoaid/priority.py
algoaid-1.0.2.dist-info/LICENSE
algoaid-1.0.2.dist-info/METADATA
algoaid-1.0.2.dist-info/WHEEL
algoaid-1.0.2.dist-info/top_level.txt
algoaid-1.0.2.dist-info/RECORD
