Metadata-Version: 2.1
Name: algoaid
Version: 1.0.2
Summary: Tools for learning about algorithms and data structures
Home-page: https://github.com/Emilostuff/algoaid
Author: Emil Skydsgaard
Author-email: emilostuff@gmail.com
Keywords: student,learning,algorithms,data,structures
Classifier: Development Status :: 3 - Alpha
Classifier: Intended Audience :: Education
Classifier: Topic :: Education
Classifier: License :: OSI Approved :: MIT License
Classifier: Programming Language :: Python :: 3
Requires-Python: >=3.8, <4
License-File: LICENSE
Requires-Dist: matplotlib
Requires-Dist: graphviz
Requires-Dist: scipy
Requires-Dist: numpy
